discordautochat/__init__.py
discordautochat/main.py
discordautochat-1.3.dist-info/LICENSE
discordautochat-1.3.dist-info/METADATA
discordautochat-1.3.dist-info/WHEEL
discordautochat-1.3.dist-info/top_level.txt
discordautochat-1.3.dist-info/RECORD
